marinerg_facility/__init__.py
marinerg_facility/admin.py
marinerg_facility/apps.py
marinerg_facility/urls.py
marinerg_facility/migrations/0001_initial.py
marinerg_facility/migrations/0002_alter_facility_image.py
marinerg_facility/migrations/0003_facility_thumbnail_equipment.py
marinerg_facility/migrations/0004_equipment_created_at_equipment_updated_at_and_more.py
marinerg_facility/migrations/0005_alter_equipment_name.py
marinerg_facility/migrations/0006_alter_equipment_name.py
marinerg_facility/migrations/0007_equipmenttag_facilitytag_equipment_tags_and_more.py
marinerg_facility/migrations/__init__.py
marinerg_facility/models/__init__.py
marinerg_facility/models/equipment.py
marinerg_facility/models/facility.py
marinerg_facility/serializers/__init__.py
marinerg_facility/serializers/equipment.py
marinerg_facility/serializers/facility.py
marinerg_facility/utils/__init__.py
marinerg_facility/utils/test_utils/__init__.py
marinerg_facility/utils/test_utils/models.py
marinerg_facility/utils/test_utils/resources.py
marinerg_facility/view_sets/__init__.py
marinerg_facility/view_sets/equipment.py
marinerg_facility/view_sets/facility.py
marinerg_facility-0.0.13.dist-info/licenses/LICENSE
marinerg_facility-0.0.13.dist-info/METADATA
marinerg_facility-0.0.13.dist-info/WHEEL
marinerg_facility-0.0.13.dist-info/top_level.txt
marinerg_facility-0.0.13.dist-info/RECORD
